LICENSE.md
README.rst
setup.py
arron_middleware.egg-info/PKG-INFO
arron_middleware.egg-info/SOURCES.txt
arron_middleware.egg-info/dependency_links.txt
arron_middleware.egg-info/requires.txt
arron_middleware.egg-info/top_level.txt
middlewares/__init__.py
middlewares/redirect_middleware.py